qsim/DMQsim.py
qsim/Qsim.py
qsim/__init__.py
qsim/qSimException.py
qsim/qcli.py
qsim/qgates.py
qsim/qgatesUtils.py
qsim/noisemodel/__init__.py
qsim/noisemodel/noiseChannels.py
qsim/noisemodel/noiseUtils.py
qusimulator-2.2.dist-info/LICENSE
qusimulator-2.2.dist-info/METADATA
qusimulator-2.2.dist-info/WHEEL
qusimulator-2.2.dist-info/entry_points.txt
qusimulator-2.2.dist-info/top_level.txt
qusimulator-2.2.dist-info/RECORD
